{
  "schema_version": 3,
  "timestamp": "2026-03-22T02:20:15.855438",
  "fingerprint": "d2526fbe478647f796d0d6e52dd19218",
  "source": "halo-scraper",
  "gametype": "oddball",
  "gametype_id": 3,
  "player_count": 8,
  "players": [
    {
      "name": " Rocky",
      "display_name": "",
      "score_string": "1:25",
      "place": 0,
      "place_string": "1st",
      "team": 1,
      "observer": false,
      "rank": -1,
      "rank_verified": -1,
      "kills": 36,
      "deaths": 25,
      "assists": 17,
      "suicides": 1,
      "kd_ratio": 1.44,
      "medals": {
        "total": 12,
        "by_type": 12545
      },
      "accuracy": {
        "total_shots": 967,
        "shots_hit": 414,
        "headshots": 21,
        "percentage": 42.812823164426064
      },
      "killed": [
        0,
        0,
        0,
        0,
        12,
        8,
        12,
        4,
        0,
        0,
        0,
        0,
        0,
        0,
        0,
        0
      ],
      "gametype_values": [
        6,
        0
      ],
      "gametype_stats": {
        "Ball Kills": 0,
        "Carrier Kills": 6
      }
    },
    {
      "name": "           Goose",
      "display_name": "",
      "score_string": "1:08",
      "place": 0,
      "place_string": "1st",
      "team": 1,
      "observer": false,
      "rank": -1,
      "rank_verified": -1,
      "kills": 22,
      "deaths": 19,
      "assists": 20,
      "suicides": 0,
      "kd_ratio": 1.1578947368421053,
      "medals": {
        "total": 3,
        "by_type": 768
      },
      "accuracy": {
        "total_shots": 830,
        "shots_hit": 367,
        "headshots": 16,
        "percentage": 44.21686746987952
      },
      "killed": [
        0,
        0,
        0,
        0,
        7,
        5,
        3,
        7,
        0,
        0,
        0,
        0,
        0,
        0,
        0,
        0
      ],
      "gametype_values": [
        2,
        0
      ],
      "gametype_stats": {
        "Ball Kills": 0,
        "Carrier Kills": 2
      }
    },
    {
      "name": "Toyota Man",
      "display_name": "",
      "score_string": " :59",
      "place": 0,
      "place_string": "1st",
      "team": 1,
      "observer": false,
      "rank": -1,
      "rank_verified": -1,
      "kills": 24,
      "deaths": 21,
      "assists": 20,
      "suicides": 0,
      "kd_ratio": 1.1428571428571428,
      "medals": {
        "total": 3,
        "by_type": 4353
      },
      "accuracy": {
        "total_shots": 989,
        "shots_hit": 360,
        "headshots": 19,
        "percentage": 36.400404448938325
      },
      "killed": [
        0,
        0,
        0,
        0,
        5,
        7,
        5,
        7,
        0,
        0,
        0,
        0,
        0,
        0,
        0,
        0
      ],
      "gametype_values": [
        0,
        0
      ],
      "gametype_stats": {
        "Ball Kills": 0,
        "Carrier Kills": 0
      }
    },
    {
      "name": "roasted",
      "display_name": "",
      "score_string": " :11",
      "place": 0,
      "place_string": "1st",
      "team": 1,
      "observer": false,
      "rank": -1,
      "rank_verified": -1,
      "kills": 17,
      "deaths": 26,
      "assists": 17,
      "suicides": 0,
      "kd_ratio": 0.6538461538461539,
      "medals": {
        "total": 2,
        "by_type": 4352
      },
      "accuracy": {
        "total_shots": 799,
        "shots_hit": 380,
        "headshots": 13,
        "percentage": 47.559449311639554
      },
      "killed": [
        0,
        0,
        0,
        0,
        3,
        5,
        5,
        4,
        0,
        0,
        0,
        0,
        0,
        0,
        0,
        0
      ],
      "gametype_values": [
        1,
        0
      ],
      "gametype_stats": {
        "Ball Kills": 0,
        "Carrier Kills": 1
      }
    },
    {
      "name": "Minerkazoo",
      "display_name": "",
      "score_string": "1:24",
      "place": 1,
      "place_string": "2nd",
      "team": 0,
      "observer": false,
      "rank": -1,
      "rank_verified": -1,
      "kills": 18,
      "deaths": 27,
      "assists": 12,
      "suicides": 0,
      "kd_ratio": 0.6666666666666666,
      "medals": {
        "total": 2,
        "by_type": 768
      },
      "accuracy": {
        "total_shots": 671,
        "shots_hit": 275,
        "headshots": 11,
        "percentage": 40.98360655737705
      },
      "killed": [
        3,
        2,
        8,
        5,
        0,
        0,
        0,
        0,
        0,
        0,
        0,
        0,
        0,
        0,
        0,
        0
      ],
      "gametype_values": [
        5,
        0
      ],
      "gametype_stats": {
        "Ball Kills": 0,
        "Carrier Kills": 5
      }
    },
    {
      "name": "Red",
      "display_name": "",
      "score_string": " :55",
      "place": 1,
      "place_string": "2nd",
      "team": 0,
      "observer": false,
      "rank": -1,
      "rank_verified": -1,
      "kills": 22,
      "deaths": 25,
      "assists": 14,
      "suicides": 1,
      "kd_ratio": 0.88,
      "medals": {
        "total": 7,
        "by_type": 257
      },
      "accuracy": {
        "total_shots": 750,
        "shots_hit": 413,
        "headshots": 15,
        "percentage": 55.06666666666666
      },
      "killed": [
        8,
        4,
        4,
        6,
        0,
        0,
        0,
        0,
        0,
        0,
        0,
        0,
        0,
        0,
        0,
        0
      ],
      "gametype_values": [
        2,
        0
      ],
      "gametype_stats": {
        "Ball Kills": 0,
        "Carrier Kills": 2
      }
    },
    {
      "name": "nico",
      "display_name": "",
      "score_string": " :24",
      "place": 1,
      "place_string": "2nd",
      "team": 0,
      "observer": false,
      "rank": -1,
      "rank_verified": -1,
      "kills": 34,
      "deaths": 25,
      "assists": 8,
      "suicides": 0,
      "kd_ratio": 1.36,
      "medals": {
        "total": 12,
        "by_type": 8961
      },
      "accuracy": {
        "total_shots": 1037,
        "shots_hit": 433,
        "headshots": 24,
        "percentage": 41.75506268081003
      },
      "killed": [
        10,
        7,
        7,
        10,
        0,
        0,
        0,
        0,
        0,
        0,
        0,
        0,
        0,
        0,
        0,
        0
      ],
      "gametype_values": [
        0,
        0
      ],
      "gametype_stats": {
        "Ball Kills": 0,
        "Carrier Kills": 0
      }
    },
    {
      "name": "TURDSONG",
      "display_name": "",
      "score_string": " :15",
      "place": 1,
      "place_string": "2nd",
      "team": 0,
      "observer": false,
      "rank": -1,
      "rank_verified": -1,
      "kills": 17,
      "deaths": 22,
      "assists": 20,
      "suicides": 0,
      "kd_ratio": 0.7727272727272727,
      "medals": {
        "total": 3,
        "by_type": 768
      },
      "accuracy": {
        "total_shots": 826,
        "shots_hit": 376,
        "headshots": 12,
        "percentage": 45.52058111380145
      },
      "killed": [
        4,
        6,
        2,
        5,
        0,
        0,
        0,
        0,
        0,
        0,
        0,
        0,
        0,
        0,
        0,
        0
      ],
      "gametype_values": [
        1,
        0
      ],
      "gametype_stats": {
        "Ball Kills": 0,
        "Carrier Kills": 1
      }
    }
  ],
  "teams": [
    {
      "team_id": 1,
      "name": "Blue Team",
      "score": 343,
      "score_string": "3:43",
      "place": 0,
      "round_score": 0
    },
    {
      "team_id": 0,
      "name": "Red Team",
      "score": 258,
      "score_string": "2:58",
      "place": 1,
      "round_score": 0
    }
  ]
}